tigrinya_numbers/__init__.py
tigrinya_numbers/constants.py
tigrinya_numbers/converter.py
tigrinya_numbers-0.2.0.dist-info/LICENSE
tigrinya_numbers-0.2.0.dist-info/METADATA
tigrinya_numbers-0.2.0.dist-info/WHEEL
tigrinya_numbers-0.2.0.dist-info/top_level.txt
tigrinya_numbers-0.2.0.dist-info/RECORD
