Metadata-Version: 2.2
Name: tigrinya-numbers
Version: 0.2.0
Summary: Convert numbers to Tigrinya words
Author-email: Fitsum Gaim <fitsum@geezlab.com>
License: CC-BY-SA-4.0
Project-URL: Homepage, https://github.com/fgaim/tigrinya-numbers
Project-URL: Issues, https://github.com/fgaim/tigrinya-numbers/issues
Keywords: tigrinya,numbers,eritrea,ethiopia,localization,i18n
Classifier: Development Status :: 4 - Beta
Classifier: Intended Audience :: Developers
Classifier: License :: Other/Proprietary License
Classifier: Operating System :: OS Independent
Classifier: Programming Language :: Python :: 3
Classifier: Programming Language :: Python :: 3.8
Classifier: Programming Language :: Python :: 3.9
Classifier: Programming Language :: Python :: 3.10
Classifier: Programming Language :: Python :: 3.11
Classifier: Programming Language :: Python :: 3.12
Classifier: Programming Language :: Python :: 3.13
Classifier: Topic :: Text Processing :: Linguistic
Requires-Python: >=3.8
License-File: LICENSE
Provides-Extra: dev
Requires-Dist: pytest>=7.0; extra == "dev"
Requires-Dist: ipykernel; extra == "dev"
